Workbook

Sheet Client Portfolio
I3: Client Name: Jason Lee
I6: Tax Year | L6: 2025
I7: Citizenship | L7: US
I8: Age | L8: 34
I9: Current Residence | L9: HK
I10: HK Tax Resident | L10: Yes
I11: Date Moved | L11: 45108
I12: Greencard | L12: No
I13: Occupation | L13: Marketing Manager
I14: Foreign Employer | L14: HK Company
I15: Foreign Bank acc | L15: 3
I16: US Bank account | L16: 1
G20: Objective: | H20: Analyze the client's US international tax compliance obligations for tax year 2025,
H21: including worldwide income reporting, foreign earned income, foreign tax considerations,
H22: foreign financial account reporting, FATCA reporting, and related documentation requirements.

Sheet Income Data
A1: ID | B1: Income Type | C1: Source | D1: Description | E1: Currency | F1: Amount | G1: FX RATE | H1: USD AMT | I1: US/FOREIGN SOURCE | J1: Workpaper | K1: Support Docs | L1: Review Status
A2: INC-001 | B2: Employment | C2: Hong Kong | D2: Annual salary from HK employer | E2: HKD | F2: 780000 | G2: 7.8 | H2: =IF(E2="USD",F2,F2/G2) -> 100000 | I2: Foreign | J2: Form 1040 / Form 2555 | K2: HK Employment Income Statement | L2: Reviewed — Initial
A3: INC-002 | B3: Interest | C3: Hong Kong | D3: Interest from HK bank accounts | E3: HKD | F3: 8500 | G3: 7.8 | H3: =IF(E3="USD",F3,F3/G3) -> 1089.7436 | I3: Foreign | J3: Form 1040 / Foreign Income | K3: HK Bank Interest Statement | L3: Reviewed — Initial
A4: INC-003 | B4: Dividend | C4: United States | D4: Dividends from US brokerage | E4: USD | F4: 4200 | G4: 1 | H4: =IF(E4="USD",F4,F4/G4) -> 4200 | I4: US | J4: Form 1040 / Investment Income | K4: US Brokerage 1099-DIV | L4: Reviewed — Initial
A5: INC-004 | B5: Capital Gain | C5: United States | D5: Gain from sale of US securities | E5: USD | F5: 7500 | G5: 1 | H5: =IF(E5="USD",F5,F5/G5) -> 7500 | I5: US | J5: Form 1040 / Capital Gains | K5: US Brokerage 1099-B | L5: Reviewed — Initial
A6: INC-005 | B6: Self-Employment | C6: Hong Kong | D6: Freelance consulting income | E6: HKD | F6: 60000 | G6: 7.8 | H6: =IF(E6="USD",F6,F6/G6) -> 7692.3077 | I6: Foreign | J6: Form 1040 / Self-Employment | K6: Consulting Income Records | L6: Reviewed — Initial
A9: Income Summary
A10: Total Income USD = | B10: =SUM(H2:H6) -> 120482.05

Sheet FX Rates
A1: Currency | B1: Currency Name | C1: USD Conversion Rate | D1: Rate Description
A2: HKD | B2: Hong Kong Dollar | C2: 7.8 | D2: 1 USD = 7.80 HKD
A3: USD | B3: US Dollar | C3: 1 | D3: Base currency
A5: Note:
A6: For this simulated engagement, an assumed annual exchange rate of
A7: USD 1 = HKD 7.80 is used consistently for illustrative calculations.
A8: Actual tax-return preparation would require the applicable exchange-rate methodology

Sheet Foreign Account
A1: Account ID | B1: Financial Institution | C1: Country | D1: Account Type | E1: Currency | F1: Highest Balance | G1: USD FX Rate | H1: Highest Balance USD | I1: Ownership | J1: Documentation | K1: Review Status
A2: FA-001 | B2: HSBC | C2: HK | D2: Bank Acc | E2: HKD | F2: 280000 | G2: 7.8 | H2: =F2/G2 -> 35897.436 | I2: Direct | J2: 2025 statement | K2: Initial Review
A3: FA-002 | B3: Hang Seng Bank | C3: HK | D3: Bank Acc | E3: HKD | F3: 145000 | G3: 7.8 | H3: =F3/G3 -> 18589.744 | I3: Direct | J3: 2025 statement | K3: Initial Review
A4: FA-003 | B4: Interactive Broker | C4: HK | D4: Broker Acc | E4: USD | F4: 38000 | G4: 1 | H4: =F4/G4 -> 38000 | I4: Direct | J4: 2025 statement | K4: Initial Review
A5: FA-004 | B5: Bank of America | C5: US | D5: Bank Acc | E5: USD | F5: 12000 | G5: 1 | H5: =F5/G5 -> 12000 | I5: Direct | J5: 2025 statement | K5: Initial Review
A8: Aggregate Foreign Account Value: | C8: =H2+H3+H4 -> 92487.179

Sheet Form 1040 WP
A1: Income Type | B1: Source | C1: USD Amount | D1: US/Foreign | E1: 1040 Treatment
A2: Employment | B2: Hong Kong | C2: ='Income Data'!H2 -> 100000 | D2: Foreign | E2: Wages
A3: Interest | B3: Hong Kong | C3: ='Income Data'!H3 -> 1089.7436 | D3: Foreign | E3: Interest income
A4: Dividend | B4: United States | C4: ='Income Data'!H4 -> 4200 | D4: US | E4: Dividend income
A5: Capital Gain | B5: United States | C5: ='Income Data'!H5 -> 7500 | D5: US | E5: Capital gain
A6: Self-Employment | B6: Hong Kong | C6: ='Income Data'!H6 -> 7692.3077 | D6: Foreign | E6: Self-employment income
A7: Total | C7: =SUM(C2:C6) -> 120482.05
A9: Foreign Sourced Income | C9: =SUMIF('Income Data'!I2:I6,"Foreign",'Income Data'!H2:H6) -> 108782.05
A10: US Sourced Income | C10: =SUMIF('Income Data'!I2:I6,"US",'Income Data'!H2:H6) -> 11700

Sheet Form 2555 WP
A1: Item | B1: Details | C1: Amount / Result
A2: Client | B2: Jason Lee
A3: Tax Year | B3: 2025
A4: Foreign Employer | B4: Hong Kong Employer
A5: Foreign Employment Income | B5: HKD 780,000
A6: Foreign Employment Income (USD) | C6: ='Income Data'!H2 -> 100000
A7: Foreign Country | B7: Hong Kong
A8: Foreign Residence Start | B8: July 1, 2023
A9: Qualifying Tax Year | B9: 2025
A10: Foreign Earned Income | C10: =C6 -> 100000
A11: Tax Home | B11: Hong Kong | C11: Meets
A12: Bona Fide Residence | B12: Hong Kong since 2023 | C12: Potentially Meets
A13: Physical Presence | B13: To be verified | C13: Review Required
A14: Foreign Earned Income Category | B14: Employment income | C14: Qualifying income category
A15: Eligibility Review | B15: Subject to applicable IRS requirements | C15: Review Required
A16: Supporting Document | B16: HK Employment Income Statement | C16: Available
A17: Review Status | B17: Initial Review | C17: Pending detailed verification

Sheet Form 1116 WP
A1: Item | B1: Details | C1: Amount / Result
A2: Client | B2: Jason Lee
A3: Tax Year | B3: 2025
A4: Foreign Country | B4: Hong Kong
A5: Foreign Earned Income | B5: Employment income | C5: ='Income Data'!H2 -> 100000
A6: Foreign Interest Income | B6: HK bank interest | C6: ='Income Data'!H3 -> 1089.7436
A7: Total Foreign Income | C7: =SUM(C5:C6) -> 101089.74
A8: Assumed Hong Kong Income Tax Paid | B8: Simulated amount for project | C8: 12000
A9: Foreign Tax Currency | B9: HKD
A10: FX Rate | B10: 1 USD = 7.80 HKD | C10: 7.8
A11: Foreign Tax Paid (USD) | C11: =C8/C10 -> 1538.4615
A12: Foreign Tax Credit | B12: Subject to limitation | C12: Review Required
A13: Credit Limitation | B13: Requires US tax calculation | C13: Review Required
A14: Excess Foreign Tax | B14: To be determined | C14: Review Required
A15: Supporting Document | B15: Simulated Hong Kong tax assessment | C15: Project Assumption
A16: Review Status | B16: Initial Review | C16: Pending detailed verification

Sheet FBAR WP
A1: Item | B1: Details | C1: Amount
A2: Client | B2: Jason Lee
A3: Tax Year | B3: 2025
A4: Filing | B4: FinCEN Form 114 (FBAR)
A5: Purpose | B5: Foreign financial account reporting analysis
A6: HSBC Hong Kong | B6: Foreign bank account | C6: 35897.44
A7: Hang Seng Bank | B7: Foreign bank account | C7: 18589.74
A8: Interactive Brokers | B8: Foreign brokerage account | C8: 38000
A9: Aggregate Foreign Account Value | C9: =SUM(C6:C8) -> 92487.18
A10: Bank of America | B10: US bank account | C10: Not Included
A11: FBAR Filing Analysis | B11: Foreign accounts exceed applicable reporting threshold | C11: Review Required
A12: Account Ownership | B12: Direct individual ownership | C12: Yes
A13: Supporting Documents | B13: 2025 bank/brokerage statements | C13: Available
A14: Review Status | B14: Initial Review | C14: Pending Verification Required

Sheet Form 8938 WP
A1: Item | B1: Analysis | C1: Result
A2: Client | B2: Jason Lee
A3: Tax Year | B3: 2025
A4: Filing Status | B4: Single
A5: Residence | B5: Hong Kong
A6: Specified Foreign Financial Assets | B6: Foreign bank and brokerage accounts | C6: yes
A7: HSBC Hong Kong | B7: Specified foreign financial asset | C7: yes
A8: Hang Seng Bank | B8: Specified foreign financial asset | C8: yes
A9: Interactive Brokers | B9: Specified foreign financial asset | C9: yes
A10: Maximum Aggregate Value | B10: $92,487.18 | C10: 92487.18
A11: US Bank Account | B11: Excluded – domestic financial account | C11: Excluded
A12: Documentation Required | B12: Bank and brokerage statements | C12: Available
A13: Threshold Assessment | B13: Requires application of Form 8938 threshold rules | C13: Review Required

Sheet W-8 , W-9 Review
A1: Document | B1: Scenario | C1: Purpose / Review
A2: W-9 | B2: US person receiving payments | C2: Confirm US taxpayer identification and certification
A3: W-8BEN | B3: Foreign individual receiving US-source income | C3: Document foreign status and applicable treaty claim
A4: W-8BEN-E | B4: Foreign entity receiving US-source income | C4: Document foreign entity status
A5: W-8ECI | B5: Foreign person claiming income effectively connected with a US trade or business | C5: Document effectively connected income claim
A6: W-8EXP | B6: Foreign tax-exempt organization | C6: Document foreign tax-exempt status
A7: W-8IMY | B7: Foreign intermediary or flow-through entity | C7: Document intermediary status and withholding information
A8: Daniel Wong | B8: US citizen individual | C8: Generally uses Form W-9 when required as a US person
A9: Review Objective | B9: Documentation classification | C9: Determine appropriate IRS withholding certificate based on payee status

Sheet Compliance Checklist
A1: Compliance Area | B1: Form / Requirement | C1: Status | D1: Key Data / Amount | E1: Review Note
A2: Worldwide Income | B2: Form 1040 | C2: Completed | D2: $120,482.05 | E2: All identified income items included in worldwide income analysis
A3: Foreign Earned Income | B3: Form 2555 | C3: In Review | D3: $100,000 | E3: Eligibility and applicable exclusion limits require verification
A4: Foreign Tax Credit | B4: Form 1116 | C4: In Review | D4: $1,538.46 | E4: Simulated foreign tax converted to USD; credit limitation requires analysis
A5: Foreign Financial Accounts | B5: FBAR / FinCEN 114 | C5: Completed | D5: $92,487.18 | E5: Three foreign accounts included in aggregate analysis
A6: FATCA Assets | B6: Form 8938 | C6: In Review | D6: $92,487.18 | E6: Specified foreign financial assets identified; threshold analysis required
A7: W-8 / W-9 Documentation | B7: W-8 / W-9 | C7: Completed | D7: N/A | E7: US person documentation classification reviewed
A8: Foreign Bank Account – HSBC | B8: FBAR | C8: Reviewed | D8: $35,897.44 | E8: Foreign account identified
A9: Foreign Bank Account – Hang Seng | B9: FBAR | C9: Reviewed | D9: $18,589.74 | E9: Foreign account identified
A10: Foreign Brokerage – Interactive Brokers | B10: FBAR / FATCA | C10: Reviewed | D10: $38,000.00 | E10: Foreign brokerage account identified
A11: US Bank Account | B11: Not applicable | C11: Reviewed | D11: $12,000.00 | E11: US account; excluded from foreign-account analysis
A12: Supporting Documents | B12: Client records | C12: Available | D12: N/A | E12: Bank, brokerage and income documentation simulated
A13: Quality Control | B13: Workpaper review | C13: In Progress | D13: N/A | E13: Cross-check calculations and conclusions
A14: Overall Compliance Review | B14: 2025 US International Tax | D14: In Progress | E14: Final review pending

Sheet Final Dashboard
A1: US INTERNATIONAL TAX COMPLIANCE
A2: 2025 CLIENT WORKPAPER DASHBOARD
A3: Client | B3: Jason Lee
A4: Tax Year | B4: 2025
A5: Residence | B5: Hong Kong
A6: Citizenship | B6: United States
A7: Filing Status | B7: Single
A10: Key Financial Metrics | B10: Amount
A11: Worldwide Income | B11: ='Form 1040 WP'!C7 -> 120482.05
A12: Foreign-Sourced Income | B12: ='Form 1040 WP'!C9 -> 108782.05
A13: US-Sourced Income | B13: ='Form 1040 WP'!C10 -> 11700
A14: Foreign Account Value | B14: ='FBAR WP'!C9 -> 92487.18
A19: OVERALL STATUS | B19: In Progress | D19: OPEN REVIEW ITEMS | E19: Status
A20: Workpaper Preparation | B20: Substantially Complete | D20: Form 2555 eligibility | E20: Review
A21: Final Technical Review | B21: Pending | D21: Form 1116 limitation | E21: Review
A22: Supporting Documentation | B22: Simulated | D22: Form 8938 threshold | E22: Review
D23: Final QC | E23: Pending
